onshape_urdf_exporter/__init__.py
onshape_urdf_exporter/__main__.py
onshape_urdf_exporter/config_file.py
onshape_urdf_exporter/features.py
onshape_urdf_exporter/load_robot.py
onshape_urdf_exporter/onshape_api/__init__.py
onshape_urdf_exporter/onshape_api/client.py
onshape_urdf_exporter/onshape_api/onshape.py
onshape_urdf_exporter/onshape_api/utils.py
onshape_urdf_exporter/robot_description.py
onshape_urdf_exporter/stl_utils.py
onshape_urdf_exporter-1.0.0.dist-info/LICENSE
onshape_urdf_exporter-1.0.0.dist-info/METADATA
onshape_urdf_exporter-1.0.0.dist-info/WHEEL
onshape_urdf_exporter-1.0.0.dist-info/entry_points.txt
onshape_urdf_exporter-1.0.0.dist-info/RECORD
