Metadata-Version: 2.1
Name: onshape-urdf-exporter
Version: 1.0.0
Summary: Exports an OnShape assembly to a URDF file with STL meshes
License: MIT
Author: Urban Machine
Author-email: info@urbanmachine.build
Requires-Python: >=3.10,<4.0
Classifier: License :: OSI Approved :: MIT License
Classifier: Programming Language :: Python :: 3
Classifier: Programming Language :: Python :: 3.10
Classifier: Programming Language :: Python :: 3.11
Classifier: Programming Language :: Python :: 3.12
Classifier: Programming Language :: Python :: 3.13
Requires-Dist: colorama (>=0.4.6,<0.5.0)
Requires-Dist: numpy (>=1.26.2,<2.0.0)
Requires-Dist: open3d (==0.16.0)
Requires-Dist: pydantic (>=2.5.2,<3.0.0)
Requires-Dist: pydantic-yaml (>=1.2.0,<2.0.0)
Requires-Dist: requests (>=2.31.0,<3.0.0)
